team_commit_checker/coding_net.py
team_commit_checker/main.py
team_commit_checker-0.1.1.dist-info/METADATA
team_commit_checker-0.1.1.dist-info/WHEEL
team_commit_checker-0.1.1.dist-info/entry_points.txt
team_commit_checker-0.1.1.dist-info/RECORD
