Metadata-Version: 2.1
Name: team-commit-checker
Version: 0.1.1
Summary: A CLI tool to check team members' git commits in coding.net.
License: MIT
Keywords: python,coding.net
Author: Zhongwei
Author-email: lizhongwei.nkcs@gmail.com
Requires-Python: >=3.9,<3.12
Classifier: License :: OSI Approved :: MIT License
Classifier: Programming Language :: Python :: 3
Classifier: Programming Language :: Python :: 3.9
Classifier: Programming Language :: Python :: 3.10
Classifier: Programming Language :: Python :: 3.11
Requires-Dist: configparser (>=6.0.0,<7.0.0)
Requires-Dist: pyinquirer (>=1.0.3,<2.0.0)
Requires-Dist: requests (>=2.31.0,<3.0.0)
